interest_sct/__init__.py
interest_sct/interest.py
interest_sct-0.1.0.dist-info/METADATA
interest_sct-0.1.0.dist-info/WHEEL
interest_sct-0.1.0.dist-info/top_level.txt
interest_sct-0.1.0.dist-info/RECORD
